parsealot/__init__.py
parsealot/__version__.py
parsealot/cli.py
parsealot/examples.py
parsealot/lib.py
tests/__init__.py
tests/conftest.py
tests/test_parsealot_main.py
parsealot-0.0.2.dist-info/LICENSE
parsealot-0.0.2.dist-info/METADATA
parsealot-0.0.2.dist-info/WHEEL
parsealot-0.0.2.dist-info/entry_points.txt
parsealot-0.0.2.dist-info/top_level.txt
parsealot-0.0.2.dist-info/zip-safe
parsealot-0.0.2.dist-info/RECORD
