Metadata-Version: 2.1
Name: parsealot
Version: 0.0.2
Summary: A Python project template.
Home-page: https://github.com/leahevy/parsealot
Author: Leah Lackner
Author-email: leah.lackner+github@gmail.com
License: GPLv3
Project-URL: Documentation, https://leahevy.github.io/parsealot
Project-URL: Source, https://github.com/leahevy/parsealot
Project-URL: Tracker, https://github.com/leahevy/parsealot/issues
Platform: Linux
Platform: Mac OSX
Classifier: Development Status :: 2 - Pre-Alpha
Classifier: Environment :: Console
Classifier: Intended Audience :: Developers
Classifier: License :: OSI Approved :: GNU General Public License v3 or later (GPLv3+)
Classifier: Operating System :: MacOS :: MacOS X
Classifier: Operating System :: POSIX :: Linux
Classifier: Programming Language :: Python :: 3.10
Requires-Python: >=3.10
License-File: LICENSE
Requires-Dist: rich (>=12.2.0)
Requires-Dist: typer (>=0.4.1)
Requires-Dist: semantic-version (>=2.10.0)
Provides-Extra: dev
Requires-Dist: darker (>=1.5.0) ; extra == 'dev'
Requires-Dist: black (>=22.3.0) ; extra == 'dev'
Requires-Dist: isort (>=5.10.1) ; extra == 'dev'
Requires-Dist: types-setuptools (>=57.4.14) ; extra == 'dev'
Requires-Dist: setuptools (>=58.1.0) ; extra == 'dev'
Requires-Dist: wheel (>=0.37.1) ; extra == 'dev'
Requires-Dist: build (>=0.8.0) ; extra == 'dev'
Requires-Dist: pytest (>=7.1.1) ; extra == 'dev'
Requires-Dist: pytest-cov (>=3.0.0) ; extra == 'dev'
Requires-Dist: flake8 (>=4.0.1) ; extra == 'dev'
Requires-Dist: mypy (>=0.942) ; extra == 'dev'
Requires-Dist: pdoc (>=12.0.2) ; extra == 'dev'
Requires-Dist: pre-commit (>=2.18.1) ; extra == 'dev'
Requires-Dist: twine (>=4.0.0) ; extra == 'dev'
Requires-Dist: bump2version (>=1.0.1) ; extra == 'dev'
Requires-Dist: gitchangelog (>=3.0.4) ; extra == 'dev'
